---
title: 8.2.4 操作数栈
tags: []
categories:
  - 编程语言
  - Java
  - Java语言
  - JVM
  - 第8章 虚拟机字节码执行引擎
  - 8.2 运行时栈帧结构
date: 2022-12-29 16:06:16
---

操作数栈，在方法执行过程中，根据字节码指令，往栈中写入数据或提取数据，即入栈/出栈

某些字节码指令将值压入操作数栈，其余的字节码指令将操作数取出栈，使用它们之后再把结果压入栈。

直接来看个具体例子：

```java
/**
 * @Author: CoachHe
 * @Date: 2022/11/25 10:00
 */
public class OperandStackTest {
    public void testAddOperation() {
        byte i = 15;
        int j = 0;
        int k = i + j;
    }
}
```

可以看到，是一个很简单的类和方法，那么我们来看看用 `javap -verbose OperandStackTest` 反编译出来的内容：

```txt
Classfile /Users/coachhe/programs/java/jvm-coachhe/Chapter8_JVMBytecodeEngine/target/classes/com/coachhe/section2_运行时栈帧结构/操作数栈/OperandStackTest.class
  Last modified 2022-11-25; size 532 bytes
  MD5 checksum d2ef1ed6453d469857e18d619fc5dd29
  Compiled from "OperandStackTest.java"
public class com.coachhe.section2_运行时栈帧结构.操作数栈.OperandStackTest
  minor version: 0
  major version: 52
  flags: ACC_PUBLIC, ACC_SUPER
Constant pool:
   #1 = Methodref          #3.#19         // java/lang/Object."<init>":()V
   #2 = Class              #20            // com/coachhe/section2_运行时栈帧结构/操作数栈/OperandStackTest
   #3 = Class              #21            // java/lang/Object
   #4 = Utf8               <init>
   #5 = Utf8               ()V
   #6 = Utf8               Code
   #7 = Utf8               LineNumberTable
   #8 = Utf8               LocalVariableTable
   #9 = Utf8               this
  #10 = Utf8               Lcom/coachhe/section2_运行时栈帧结构/操作数栈/OperandStackTest;
  #11 = Utf8               testAddOperation
  #12 = Utf8               i
  #13 = Utf8               B
  #14 = Utf8               j
  #15 = Utf8               I
  #16 = Utf8               k
  #17 = Utf8               SourceFile
  #18 = Utf8               OperandStackTest. java
  #19 = NameAndType        #4:#5          // "<init>":()V
  #20 = Utf8               com/coachhe/section2_运行时栈帧结构/操作数栈/OperandStackTest
  #21 = Utf8               java/lang/Object
{
  public com.coachhe.section2_运行时栈帧结构.操作数栈.OperandStackTest();
    descriptor: ()V
    flags: ACC_PUBLIC
    Code:
      stack=1, locals=1, args_size=1
         0: aload_0
         1: invokespecial #1                  // Method java/lang/Object."<init>":()V
         4: return
      LineNumberTable:
        line 7: 0
      LocalVariableTable:
        Start  Length  Slot  Name   Signature
            0       5     0  this   Lcom/coachhe/section2_运行时栈帧结构/操作数栈/OperandStackTest;

  public void testAddOperation();
    descriptor: ()V
    flags: ACC_PUBLIC
    Code:
      stack=2, locals=4, args_size=1
         0: bipush        15
         2: istore_1
         3: iconst_0
         4: istore_2
         5: iload_1
         6: iload_2
         7: iadd
         8: istore_3
         9: return
      LineNumberTable:
        line 9: 0
        line 10: 3
        line 11: 5
        line 12: 9
      LocalVariableTable:
        Start  Length  Slot  Name   Signature
            0      10     0  this   Lcom/coachhe/section2_运行时栈帧结构/操作数栈/OperandStackTest;
            3       7     1     i   B
            5       5     2     j   I
            9       1     3     k   I
}
SourceFile: "OperandStackTest. java"
```

可以看到，

```java
         0: bipush        15
         2: istore_1
         3: iconst_0
         4: istore_2
         5: iload_1
         6: iload_2
         7: iadd
         8: istore_3
         9: return
```

这部分对应的是 `testAddOperation()` 方法对应的字节码指令。这些指令在运行时会被加载到虚拟机栈中进行运行

## 栈顶缓存技术

基于栈式的虚拟机所需要使用的零地址指令更加紧凑，但完成一项操作的时候必然需要使用更多的入栈和出栈指令，这同时也就意味着更多的指令分派次数和内存读/写速度。

由于操作数是存储在内存中的，因此频繁地执行内存读/写操作必然会影响执行速度。为了解决这个问题，HotSpot JVM 的设计者们提出了栈顶缓存技术，将**栈顶元素全部缓存在屋里 CPU 的寄存器中**，以此降低为内存的读/写次数，提升执行引擎的执行效率。

