---
title: 2. 重载 + 与StringBuilder与intern
tags: []
categories:
  - 编程语言
  - Java
  - Java语言
  - Java语法
  - OnJava8
  - 第18章 字符串
date: 2022-12-15 01:50:09
---

在上一节 [[1. 字符串概述]]中我们知道，`String` 对象是不可变的，因此我们可以根据需要为特定的 `String` 设置多个别名。因为 `String` 是只读的，指向它的任何引用都不可能改变它的值，所以引用之间不会相互影响。

不可变性可能会带来效率问题。

# 字符串重载

一个典型的例子是操作符 `+`，它针对 `String` 对象做了重载。==操作符重载==意味着在与特定类一起使用时，相应的操作符具有额外的意义。（应用于 `String` 的 `+` 和 `+=` 是 Java 中仅有的被重载的操作符，Java 中不允许程序员重构其他操作符）

`+` 操作可以用来拼接字符串

拼接的具体细节可以参考[[补充-String和字符串常量池]]

# append 测试

来看段代码：

```java
    //  append测试，代表直接用StringBuilder效率更高  
    @Test  
    public void ConcatenationTest4(){  
        long start = System.currentTimeMillis();  
  
        int highLevel = 100000;  
  
//        method1(highLevel); //花费的时间为：4936  
        method2(highLevel); //花费的时间为：4  
  
        long end = System.currentTimeMillis();  
  
        System.out.println("花费的时间为：" + (end - start));  
    }  
  
    // 直接使用字符串拼接  
    public void method1(int highLevel) {  
        String src = "";  
        for (int i = 0; i < highLevel; i++) {  
            src = src + "a"; // 每次循环都会创建一个StringBuilder  
        }  
    }  
  
    // 使用StringBuilder的append操作  
    public void method2(int highLevel) {  
        // 只需要创建一个StringBuilder  
        StringBuilder src = new StringBuilder();  
        for (int i = 0; i < highLevel; i++) {  
            src.append("a");  
        }  
    }
```

可以看到，两个方法花费的时间分别为 4936 毫秒和 4 毫秒，效率差别非常大。

解释：
- 使用 `StringBuilder` 的 `append()` 方式，自始至终只创建了一个 `StringBuilder` 对象
- 使用 `String` 的字符串拼接方式，创建了多个 `StringBuilder`，速度比较慢。此外，由于内存中创建了较多的 `StringBuilder` 和 `String` 对象，内存占用更大，进行 GC 还需要额外的时间。

从字节码角度来看：

先看看 method1 的字节码：

```java
// method1
 0 ldc #23
 2 astore_2
 3 iconst_0
 4 istore_3
 5 iload_3
 6 iload_1
 7 if_icmpge 36 (+29)
10 new #9 <java/lang/StringBuilder>
13 dup
14 invokespecial #10 <java/lang/StringBuilder.<init> : ()V>
17 aload_2
18 invokevirtual #11 <java/lang/StringBuilder.append : (Ljava/lang/String;)Ljava/lang/StringBuilder;>
21 ldc #14 <a>
23 invokevirtual #11 <java/lang/StringBuilder.append : (Ljava/lang/String;)Ljava/lang/StringBuilder;>
26 invokevirtual #12 <java/lang/StringBuilder.toString : ()Ljava/lang/String;>
29 astore_2
30 iinc 3 by 1
33 goto 5 (-28)
36 return
```

可以看到，第 7 行和第 33 行构成了一个循环，每次循环的都会新建一个 `StringBuilder`，然后调用 `toString` 又会创建一个 `String` 对象。

再看看 method2 的字节码：

```java
 0 new #9 <java/lang/StringBuilder>
 3 dup
 4 invokespecial #10 <java/lang/StringBuilder.<init> : ()V>
 7 astore_2
 8 iconst_0
 9 istore_3
10 iload_3
11 iload_1
12 if_icmpge 28 (+16)
15 aload_2
16 ldc #14 <a>
18 invokevirtual #11 <java/lang/StringBuilder.append : (Ljava/lang/String;)Ljava/lang/StringBuilder;>
21 pop
22 iinc 3 by 1
25 goto 10 (-15)
28 return
```

可以看到，第 12 行和第 25 行构成了一个循环，在循环中没有新对象的生成，只调用了 `append()` 方法。因此效率会比 method1 好很多。

## 优化方案

如果一开始可以预估 `StringBuilder` 的长度，可以预先设置好，避免频繁进行扩容。

# toString() 的技巧

通常我们不会去动 `toString()` 方法，当创建 `toString()` 方法时，如果操作很简单，通常可以依赖编译器，让它以合理的方式自行构建结果。但如果涉及循环，并且对性能也有一定要求，那就需要再 `toString` 中显式使用 `StringBuilder` 了。





